{
  "doc": "step7-implementation-summary.md",
  "features": [
    "Automated integration and unit tests",
    "Test environment setup and CI",
    "Comprehensive documentation and troubleshooting"
  ],
  "migrationStatus": "in-progress",
  "notes": [
    "Port test infrastructure and CI setup to Electron build.",
    "Ensure all integration/unit tests and documentation are updated for Electron context.",
    "Troubleshooting and validation scripts must be adapted for Electron modules."
  ],
  "electronIntegration": [
    "electron/test: Test infrastructure and CI setup (to be created)",
    "electron/docs: Documentation and troubleshooting (to be created)"
  ],
  "testCoverage": "pending"
}